SETUP.py
setup.py
my_pieniodzis_lib.egg-info/PKG-INFO
my_pieniodzis_lib.egg-info/SOURCES.txt
my_pieniodzis_lib.egg-info/dependency_links.txt
my_pieniodzis_lib.egg-info/top_level.txt