Metadata-Version: 2.1
Name: my-pieniodzis-lib
Version: 0.0.1
Summary: Super test libary
Home-page: UNKNOWN
Author: Maciej
License: UNKNOWN
Platform: UNKNOWN
